<?xml version="1.0"?>
<package>
    <name>algoliasearch</name>
    <version>1.5.2</version>
    <stability>stable</stability>
    <license uri="https://github.com/algolia/algoliasearch-magento/blob/master/LICENSE.txt">MIT</license>
    <channel>community</channel>
    <extends/>
    <summary>This module let you easily integrate the Algolia Search API to your Magento instance.</summary>
    <description>Algolia Search is a search API that provides hosted full-text, numerical and faceted search. Algolia&#x2019;s Search API makes it easy to deliver a great search experience in your apps &amp; websites.&#xD;
&#xD;
This extension replaces Magento's FullText Search module and provide an as-you-type auto-completion menu in your searchbar.&#xD;
</description>
    <notes>=====  BREAKING CHANGE =====&#xD;
&#xD;
A full reindex of the product indexer is needed&#xD;
&#xD;
============================&#xD;
&#xD;
- NEW: handle multiple currencies&#xD;
- UPDATED: improve errors/warnings for reindexing &#xD;
- FIX: handle both secure and unsecure base url for images&#xD;
- FIX: ability to have only instant search&#xD;
- FIX: method to get product and categories url</notes>
    <authors><author><name>Algolia Team</name><user>algolia</user><email>support@algolia.com</email></author></authors>
    <date>2016-01-08</date>
    <time>09:44:49</time>
    <contents><target name="mageetc"><dir name="modules"><file name="Algolia_Algoliasearch.xml" hash="76f2e6750adcb532438d3a9ac9b6d903"/></dir></target><target name="magecommunity"><dir name="Algolia"><dir name="Algoliasearch"><dir name="Block"><dir name="System"><dir name="Config"><dir name="Form"><dir name="Field"><file name="Custompages.php" hash="f87a9cf7b5559717cd9d6570374dcda7"/><file name="Customrankingcategory.php" hash="6d9575c12dbaecf9054de1cf12736025"/><file name="Customrankingproduct.php" hash="6d1b145e37c4f22d5b56f5783ac47511"/><file name="Customsortorder.php" hash="786c8f8fca2e4b41b8732f5fe270491b"/><file name="Customsortordercategory.php" hash="9908ea7f463138d3047c51b98591db9c"/><file name="Customsortorderproduct.php" hash="ee62901a3911bb7784467e1ca5cd8e84"/><file name="Facets.php" hash="b8c6217811a1c9afd64119d2b021cc5f"/><file name="Sections.php" hash="7aa62da4fb45f693bf81ad4aa0421ac3"/><file name="Select.php" hash="6e3cb4c1798775048bebbdc878e90aa9"/><file name="Sorts.php" hash="fede73c4ecbe39bf0344fbf6de46ed95"/></dir></dir></dir></dir></dir><dir name="Helper"><file name="Algoliahelper.php" hash="ff48a4929fffd913da57868457ace02f"/><file name="Config.php" hash="d4d0fa19e163fbb89a7420d5213420f8"/><file name="Data.php" hash="b2be5b2eab045fba6f69b33664c94f6c"/><dir name="Entity"><file name="Additionalsectionshelper.php" hash="d4f67429e539e9ee9a5365ba45808770"/><file name="Categoryhelper.php" hash="8a3caaa6a8e988d1ffd8c11486944535"/><file name="Helper.php" hash="85d9be2a624e882996cb27fc0ff38826"/><file name="Pagehelper.php" hash="b9ccdbdc677eae9442741f96d648d991"/><file name="Producthelper.php" hash="c0300fc18f305ee7391ccf39a4f86751"/><file name="Suggestionhelper.php" hash="6bbc72c1bbc17b13f8d9be1e0bb46fa2"/></dir><file name="Image.php" hash="876292c0612fa87194d1657a7facb916"/><file name="Logger.php" hash="fede0bd23b1beff2520d361293217834"/></dir><dir name="Model"><dir name="Indexer"><file name="Algolia.php" hash="0f8605eefc69a695a6ff7950d5f0c704"/><file name="Algoliaadditionalsections.php" hash="3113413441afccba3b8e79aa9fd8cdb1"/><file name="Algoliacategories.php" hash="2ea6c01f00d2d63d03fd0b62e6be78ae"/><file name="Algoliapages.php" hash="26ea3afee58d07b721c5cd74b3d6c4e3"/><file name="Algoliaqueuerunner.php" hash="24a0a2ed25e12ba5b9167b26c10b0add"/><file name="Algoliasuggestions.php" hash="7020d40bae60469d0acc7138ee72a419"/></dir><file name="Observer.php" hash="73ee1e9eb227085407bd130a4665a3ab"/><file name="Queue.php" hash="a0d83991ac0ea9cc66770cff9c9b9e7d"/><dir name="Resource"><file name="Engine.php" hash="d550dabcdc8ede0c96b6192e832de2a2"/><dir name="Fulltext"><file name="Collection.php" hash="cf6c1b8ecaea31619db8186ccae8a2d4"/></dir><file name="Fulltext.php" hash="01d762ee24691ab5560505d94286f904"/></dir><dir name="System"><file name="Imagetype.php" hash="5fd4dbd98818a15b0253c5988a65a785"/><file name="Removewords.php" hash="25408eb3e3d278da2f2ec1a6b6e6d8e8"/></dir></dir><dir name="etc"><file name="adminhtml.xml" hash="ea4176ed43885e531f90d1f5369f29ee"/><file name="config.xml" hash="aa05552daa96cbdd83b9c1bd607ec365"/><file name="system.xml" hash="79d8f689d303548c37f1ba39d34e8d24"/></dir><dir name="sql"><dir name="algoliasearch_setup"><file name="mysql4-install-0.1.0.php" hash="fffd964f9c60be7909ec216260c37ba0"/><file name="mysql4-upgrade-0.1.0-1.4.8.php" hash="5224f8f1031a0659c64d393392a7f199"/><file name="mysql4-upgrade-1.4.8-1.5.0.php" hash="fa8be181b2d43e955e75dce1ed4a19ca"/></dir></dir></dir></dir></target><target name="magedesign"><dir name="frontend"><dir name="base"><dir name="default"><dir name="layout"><file name="algoliasearch.xml" hash="28b9676bd76adfdbb9eecb54ce9c5f02"/></dir><dir name="template"><dir name="algoliasearch"><file name="beforecontent.phtml" hash="19f2ee9532f4e46c77ade0157976b780"/><file name="beforetopsearch.phtml" hash="2f9a42fa61b0f2be0bc2452ca924c2fb"/><file name="frontjs.phtml" hash="7d2cdf7bb5c2f47c0f118eac0ba1ead1"/><file name="topsearch.phtml" hash="f6d967f9170670ea8622bee66f0839df"/></dir></dir></dir></dir></dir><dir name="adminhtml"><dir name="default"><dir name="default"><dir name="template"><dir name="algoliasearch"><file name="adminjs.phtml" hash="a5842a5c608c1496060dd4610c5c774f"/></dir></dir><dir name="layout"><file name="algoliasearch.xml" hash="312ecb88cb4ae694d098bda8f580d29e"/></dir></dir></dir></dir></target><target name="mageskin"><dir name="frontend"><dir name="base"><dir name="default"><dir name="algoliasearch"><file name="algolia-admin-menu.png" hash="9202a559c30a43d4d4bbc2f9ee774fd9"/><file name="algolia-logo.png" hash="190884b3e8652f3517754ae15bca31de"/><file name="algoliasearch.css" hash="1e1a02b6a19bb45ccc00f77235e09f75"/><file name="cross-circle.png" hash="a9ae2fa7ec458ffaf7c32613ca9593da"/><file name="cross.png" hash="a046cd95cba9761c824063fbd30a26b5"/><dir name="images"><file name="ui-bg_diagonals-thick_18_b81900_40x40.png" hash="62568c006bb1066f40fd5f9cfe4489be"/><file name="ui-bg_diagonals-thick_20_666666_40x40.png" hash="406541454ec466d93217826588335194"/><file name="ui-bg_flat_10_000000_40x100.png" hash="85243ed808c91ae60d33bda3a6bdee3c"/><file name="ui-bg_glass_100_f6f6f6_1x400.png" hash="f912ffca9b1919ab26c64cf1332c5322"/><file name="ui-bg_glass_100_fdf5ce_1x400.png" hash="a9b41e3f4db0fb9be1cd2c649deb253f"/><file name="ui-bg_glass_65_ffffff_1x400.png" hash="ff9e9b45e03f11808144324fd5350612"/><file name="ui-bg_gloss-wave_35_f6a828_500x100.png" hash="08ece8908c07b1c0d18b8db076ff50fc"/><file name="ui-bg_highlight-soft_100_eeeeee_1x100.png" hash="72fe4b0e1bbb83dfd6787989d3583fbe"/><file name="ui-bg_highlight-soft_75_ffe45c_1x100.png" hash="81262299ac7f591fd1763c1ccee0691f"/><file name="ui-icons_222222_256x240.png" hash="3a3c5468f484f07ac4a320d9e22acb8c"/><file name="ui-icons_228ef1_256x240.png" hash="92b29683b6a48eae7de7eb4b1cfa039c"/><file name="ui-icons_ef8c08_256x240.png" hash="f492970693640894fb54166c75dd2925"/><file name="ui-icons_ffd27a_256x240.png" hash="dda1b6f694b0d196aefc66a1d6d758f6"/><file name="ui-icons_ffffff_256x240.png" hash="41612b0f4a034424f8321c9f824a94da"/></dir></dir></dir></dir></dir></target><target name="mage"><dir name="js"><dir name="algoliasearch"><file name="Function.prototype.bind.js" hash="eb15975feb0cc976face88cb194294ae"/><file name="admin_scripts.js" hash="877a9fcbc5d3d627772464a9311ae0b3"/><file name="algoliaAdminBundle.min.js" hash="7cbce3614ccb065595a5c2ff56e32419"/><file name="algoliaBundle.min.js" hash="c81fc78bf11c34d73dddc5600611dc47"/></dir></dir><dir name="lib"><dir name="AlgoliaSearch"><file name="AlgoliaException.php" hash="4acaa7c9142e19d1084295a3b8ba18e2"/><file name="Client.php" hash="11ad687a9868a9f574ae6a069800dd2c"/><file name="ClientContext.php" hash="77d2449636d263162460a7ccaea4e6b6"/><file name="Index.php" hash="5c1eacc54cd503bff296e9bbbd402895"/><file name="Version.php" hash="0c37eb6324361991364e0efd2696e56d"/><dir name="resources"><file name="ca-bundle.crt" hash="47961e7ef15667c93cd99be01b51f00a"/></dir></dir></dir></target></contents>
    <compatible/>
    <dependencies><required><php><min>5.2.0</min><max>6.0.0</max></php></required></dependencies>
</package>
